loglog/colors.py
loglog/log.py
loglog/loglog_error.py
loglog-0.0.1.dist-info/LICENSE
loglog-0.0.1.dist-info/METADATA
loglog-0.0.1.dist-info/WHEEL
loglog-0.0.1.dist-info/top_level.txt
loglog-0.0.1.dist-info/RECORD
