Metadata-Version: 2.1
Name: loglog
Version: 0.0.1
Summary: A small, charming and pretty logging library
Author-email: hwelsters <redacted@redacted.redacted>
Project-URL: Homepage, https://github.com/hwelsters/loglog
Project-URL: Bug Tracker, https://github.com/hwelsters/loglog/issues
Requires-Python: >=3.7
License-File: LICENSE
Requires-Dist: colored (>=1.4.4)
